catplayer.py
catplayer-0.1.0.dist-info/METADATA
catplayer-0.1.0.dist-info/WHEEL
catplayer-0.1.0.dist-info/entry_points.txt
catplayer-0.1.0.dist-info/top_level.txt
catplayer-0.1.0.dist-info/RECORD
