Metadata-Version: 2.1
Name: catplayer
Version: 0.1.0
Summary: MP4 player using moviepy and pygame
Home-page: UNKNOWN
Author: UNKNOWN
Author-email: UNKNOWN
License: UNKNOWN
Platform: UNKNOWN
Requires-Dist: moviepy
Requires-Dist: pygame
